pytest_service/VERSION
pytest_service/__init__.py
pytest_service/base.py
pytest_service/mongo.py
pytest_service/pg.py
pytest_service/py.typed
pytest_service/redis.py
pytest_service/utils.py
pytest_service-0.0.2.dist-info/LICENSE
pytest_service-0.0.2.dist-info/METADATA
pytest_service-0.0.2.dist-info/WHEEL
pytest_service-0.0.2.dist-info/entry_points.txt
pytest_service-0.0.2.dist-info/top_level.txt
pytest_service-0.0.2.dist-info/RECORD
