Metadata-Version: 2.1
Name: pytest_service
Version: 0.0.2
License: MIT License
Project-URL: homepage, https://github.com/anna-money/pytest-service
Project-URL: changelog, https://github.com/anna-money/pytest-service/blob/master/CHANGELOG.md
Classifier: License :: OSI Approved :: MIT License
Classifier: Intended Audience :: Developers
Classifier: Programming Language :: Python :: 3
Classifier: Programming Language :: Python :: 3 :: Only
Classifier: Programming Language :: Python :: 3.10
Classifier: Programming Language :: Python :: 3.11
Classifier: Programming Language :: Python :: 3.12
Classifier: Operating System :: OS Independent
Classifier: Development Status :: 5 - Production/Stable
Classifier: Framework :: Pytest
Requires-Python: >=3.10
License-File: LICENSE
Requires-Dist: pytest >=6.0.0
Requires-Dist: docker >=6.1.0
Requires-Dist: requests <2.33.0
